ansible_keepalived_config/__init__.py
ansible_keepalived_config/ansible_keepalived_config.py
ansible_keepalived_config-0.1.0.dist-info/licenses/LICENSE
ansible_keepalived_config-0.1.0.dist-info/METADATA
ansible_keepalived_config-0.1.0.dist-info/WHEEL
ansible_keepalived_config-0.1.0.dist-info/top_level.txt
ansible_keepalived_config-0.1.0.dist-info/RECORD
