Metadata-Version: 2.4
Name: ansible-keepalived-config
Version: 0.1.0
Home-page: https://github.com/Slinred/ansible-keepalived-config
Author: Nils Weyand
License: GNU GENERAL PUBLIC LICENSE
Requires-Python: >=3.10
License-File: LICENSE
Requires-Dist: ansible-core
Requires-Dist: keepalived-config
Dynamic: author
Dynamic: description
Dynamic: description-content-type
Dynamic: home-page
Dynamic: license
Dynamic: license-file
Dynamic: requires-dist
Dynamic: requires-python
